{
  "combined_text_snippet": "SHIPPER/VENDOR South Service Trading S/A Av. Cristovao Colombo, 1700 - CJ 201 CNPJ: 93.101.632/0001-22 – Porto Alegre/RS/Brasil Fone 55 51 3393.5200 Home Page: www.southservice.com.br\nCOMMERCIAL INVOICE\nInvoice No: 396414\nIssued Date: November 12th, 2025\nAplicant: BRAVO(cid:9)INTERNATIONAL DISTRIBUTION LLC 15805 BISCAYNE BLVD - SUITE 201 AVENTURA FLORIDA, 33160 UNITED STATES OF AMERICA\nConsignee / Notify CREATIVE LOGISTICS GLOBAL LIMITED RM 703A, 7/F, PROFIT INDUSTRIAL BUILDING NO. 1-15, KWAI FUNG CRESCENT, KWAI CHUNG, N.T. HONG KONG\nDescription of Goods:\n01 x 40 REFFER CONTAINER SAID TO CONTAIN 1069 CARTONS BOXES CONTAINING FROZEN FOODSTUFF COOKED AS PER PROFORMA INVOICE 090/2025 AS FOLLOWS:\nPurchase Order: PR 36554-25\nDescription of Goods\nKG\nUnit Price - USD\nSubtotal Price - USD\nFROZEN BEEF AORTA FROZEN BEEF OMASUM FROZEN BEEF TENDON FROZEN BEEF HONEYCOMB FROZEN BEEF TRIPES TOTAL\n2000,000 6000,000 3000,000 4000,000 12000,000 27.000,00\n4,48 4,48 2,47 4,48 2,40\n$ $ $ $ $\n8.960,00 26.880,00 7.410,00 17.920,00 28.800,00\nTOTAL FOB FREIGHT INSURANCE TOTAL CFR\nUSD\n$\n89.970,00\n89.970,00\nEIGHTY-NINE THOUSAND NINE HUNDRED HUNDRED SEVENTY US DOLLARS 00/100.\nADVANCE PAYMENT OF 30% PAID ON NOVEMBER 7TH, 2025: BALANCE TO PAID AGAINST COPY OF DOCUMENTS:\n$ $\n26.956,00 63.014,00\nPayment Terms: TT 30% USD IN ADVANCE AND 70% COPY BL\nPLEASE SEND THE PAYMENT DIRECTLY TO: PAY TO (Intermediary Bank) : STANDARD CHARTERED BANK NEW YORK - NY - USA SWIFT CODE: SCBLUS33 ACCOUNT NR: 3544-030205-001 BENEFICIARY´S BANK: BANCO ITAÚ BBA S.A. SÃO PAULO - SP - BRASIL SWIFT CODE: ITAUBRSPNHO IBAN: BR29 6070 1190 0028 0000 0245 622C 1 FURTHER CREDIT: SOUTH SERVICE TRADING S/A AGÊNCIA: 280 / CONTA: 24562-2 PORTO ALEGRE - RS - BRASIL DETAILS OF CHARGES (71A): OUR\nPort of loading: Port of discharge: HONG KONG, HK Incoterm: Freight: Vessel / Voyage: Net Weight: Gross Weight: Actual m3: Containers nº: NCM:\nNAVEGANTES, SC, BR\nCFR PREPAID CMA CGM BELEM 0BDMDE1MA 27.000,00 KG ,00 KG ,00 M³ 1x40' HC / GCXU8012525\nSOUTH SERVICE TRADING S/A\nBENEFICIARY/SHIPPER: South Service Trading S/A Av. Cristovao Colombo, 1700 - CJ 201 CNPJ: 93.101.632/0001-22 – Porto Alegre/RS/Brasil Fone 55 51 3393.5200 Home Page: www.southservice.com.br\nPACKING LIST FOR COMMERCIAL INVOICE\nInvoice No: 396414\nIssued Date: November 12th, 2025\nAplicant: BRAVO(cid:9)INTERNATIONAL DISTRIBUTION LLC 15805 BISCAYNE BLVD - SUITE 201 AVENTURA FLORIDA, 33160\nConsigned: CREATIVE LOGISTICS GLOBAL LIMITED RM 703A, 7/F, PROFIT INDUSTRIAL BUILDING NO. 1-15, KWAI FUNG CRESCENT, KWAI CHUNG, N.T. HONG KONG\nDescription of Goods: 01 x 40 REFFER CONTAINER SAID TO CONTAIN 1069 CARTONS BOXES CONTAINING\nFROZEN FOODSTUFF COOKED AS PER PROFORMA INVOICE 090/2025 AS FOLLOWS:\nPurchase Order: PR 36554-25\nDescription of Goods FROZEN BEEF AORTA FROZEN BEEF OMASUM FROZEN BEEF TENDON FROZEN BEEF HONEYCOMB FROZEN BEEF TRIPES TOTAL\nKG 2000,000 6000,000 3000,000 4000,000 12000,000 27000,000\nCARTONS\n0\nNET WEIGHT 2.000,000 6.000,000 3.000,000 4.000,000 12.000,000 27.000,00\nGROSS WEIGHT CONTANIER\nGCXU8012525\n0,000\nIncoterm: Port of loading: Port of discharge: Freight: Vessel / Voyage: Net Weight: Gross Weight: Actual m3: NCM:\nCFR NAVEGANTES, SC, BR HONG KONG, HK PREPAID CMA CGM BELEM 0BDMDE1MA 27.000,00 KG ,00 KG ,00 M³\n0\nSOUTH SERVICE TRADING S/A\nTARE\n4450\nSEAL\nBZ094568\nSHIPPER/VENDOR\nSouth Service Trading S/A\nAv. Cristovao Colombo, 1700 - CJ 201\nCNPJ: 93.101.632/0001-22 – Porto Alegre/RS/Brasil\nFone 55 51 3393.5200\nHome Page: www.southservice.com.br\nCOMMERCIAL INVOICE\nInvoice No: 396414 Issued Date: November 12th, 2025\nAplicant: Consignee / Notify\nBRAVO(cid:9)INTERNATIONAL DISTRIBUTION LLC CREATIVE LOGISTICS GLOBAL LIMITED\n15805 BISCAYNE BLVD - SUITE 201 RM 703A, 7/F, PROFIT INDUSTRIAL BUILDING\nAVENTURA NO. 1-15, KWAI FUNG CRESCENT, KWAI CHUNG, N.T.\nFLORIDA, 33160 HONG KONG\nUNITED STATES OF AMERICA\nDescription of Goods: 01 x 40 REFFER CONTAINER SAID TO CONTAIN 1069 CARTONS BOXES CONTAINING\nFROZEN FOODSTUFF COOKED\nAS PER PROFORMA INVOICE 090/2025 AS FOLLOWS:\nPurchase Order: PR 36554-25\nDescription of Goods KG Unit Price - USD Subtotal Price - USD\nFROZEN BEEF AORTA 2000,000 4,48 $ 8 .960,00\nFROZEN BEEF OMASUM 6000,000 4,48 $ 2 6.880,00\nFROZEN BEEF TENDON 3000,000 2,47 $ 7 .410,00\nFROZEN BEEF HONEYCOMB 4000,000 4,48 $ 1 7.920,00\nFROZEN BEEF TRIPES 12000,000 2,40 $ 2 8.800,00\nTOTAL 27.000,00\nTOTAL FOB USD 8 9.970,00\nFREIGHT\nINSURANCE\nTOTAL CFR $ 8 9.970,00\nEIGHTY-NINE THOUSAND NINE HUNDRED HUNDRED SEVENTY US DOLLARS 00/100.\nADVANCE PAYMENT OF 30% PAID ON NOVEMBER 7TH, 2025: $ 26.956,00\nBALANCE TO PAID AGAINST COPY OF DOCUMENTS: $ 63.014,00\nPayment Terms: TT 30% USD IN ADVANCE AND 70% COPY BL\nPLEASE SEND THE PAYMENT DIRECTLY TO:\nPAY TO (Intermediary Bank) : STANDARD CHARTERED BANK\nNEW YORK - NY - USA\nSWIFT CODE: SCBLUS33 ACCOUNT NR: 3544-030205-001\nBENEFICIARY´S BANK: BANCO ITAÚ BBA S.A.\nSÃO PAULO - SP - BRASIL\nSWIFT CODE: ITAUBRSPNHO IBAN: BR29 6070 1190 0028 0000 0245 622C 1\nFURTHER CREDIT: SOUTH SERVICE TRADING S/A\nAGÊNCIA: 280 / CONTA: 24562-2\nPORTO ALEGRE - RS - BRASIL\nDETAILS OF CHARGES (71A): OUR\nPort of loading: NAVEGANTES, SC, BR\nPort of discharge: HONG KONG, HK\nIncoterm: CFR\nFreight: PREPAID\nVessel / Voyage: CMA CGM BELEM 0BDMDE1MA\nNet Weight: 27.000,00 KG\nGross Weight: ,00 KG\nActual m3: ,00 M³\nContainers nº: 1x40' HC / GCXU8012525\nNCM:\nSOUTH SERVICE TRADING S/A\nBENEFICIARY/SHIPPER:\nSouth Service Trading S/A\nAv. Cristovao Colombo, 1700 - CJ 201\nCNPJ: 93.101.632/0001-22 – Porto Alegre/RS/Brasil\nFone 55 51 3393.5200\nHome Page: www.southservice.com.br\nPACKING LIST FOR COMMERCIAL INVOICE\nInvoice No: 396414 Issued Date: November 12th, 2025\nAplicant: Consigned:\nBRAVOI(cid:9)NTERNATIONAL DISTRIBUTION LLC CREATIVE LOGISTICS GLOBAL LIMITED\n15805 BISCAYNE BLVD - SUITE 201 RM 703A, 7/F, PROFIT INDUSTRIAL BUILDING\nAVENTURA NO. 1-15, KWAI FUNG CRESCENT, KWAI CHUNG, N.T.\nFLORIDA, 33160 HONG KONG\nDescription of Goods: 01 x 40 REFFER CONTAINER SAID TO CONTAIN 1069 CARTONS BOXES CONTAINING\nFROZEN FOODSTUFF COOKED\nAS PER PROFORMA INVOICE 090/2025 AS FOLLOWS:\nPurchase Order: PR 36554-25\nDescription of Goods KG CARTONS NET WEIGHT GROSS WEIGHT CONTANIER TARE SEAL\nFROZEN BEEF AORTA 2000,000 2.000,000\nFROZEN BEEF OMASUM 6000,000 6.000,000\nFROZEN BEEF TENDON 3000,000 3.000,000 GCXU8012525 4450 BZ094568\nFROZEN BEEF HONEYCOMB 4000,000 4.000,000\nFROZEN BEEF TRIPES 12000,000 12.000,000\nTOTAL 27000,000 0 27.000,00 0,000\nIncoterm: CFR\nPort of loading: NAVEGANTES, SC, BR\nPort of discharge: HONG KONG, HK\nFreight: PREPAID\nVessel / Voyage: CMA CGM BELEM 0BDMDE1MA\nNet Weight: 27.000,00 KG\nGross Weight: ,00 KG\nActual m3: ,00 M³\nNCM: 0\nSOUTH SERVICE TRADING S/A\nSHIPPER/VENDOR\nSouth Service Trading S/A\nAv. Cristovao Colombo,  1700  - CJ 201\nCNPJ: 93.101.632/0001-22  –  Porto Alegre/RS/Brasil\nFone 55 51 3393.5200  \nHome Page: www.southservice.com.br\nInvoice No: 396414\nIssued Date: November 12th, 2025\nAplicant: \nConsignee / Notify\nBRAVO\tINTERNATIONAL DISTRIBUTION LLC\nCREATIVE LOGISTICS GLOBAL LIMITED\n15805 BISCAYNE BLVD - SUITE 201\nRM 703A, 7/F, PROFIT INDUSTRIAL BUILDING\nAVENTURA\nNO. 1-15, KWAI FUNG CRESCENT, KWAI CHUNG, N.T.\nFLORIDA, 33160\nHONG KONG\nUNITED STATES OF AMERICA\nDescription of Goods:\n01 x 40 REFFER CONTAINER SAID TO CONTAIN 1069 CARTONS BOXES CONTAINING \nFROZEN FOODSTUFF COOKED\nAS PER PROFORMA INVOICE 090/2025 AS FOLLOWS:\nPurchase Order: PR 36554-25\nKG\nUnit Price - USD\nSubtotal Price - USD\n2000,000\n4,48\n8.960,00\n$                           \n6000,000\n4,48\n26.880,00\n$                         \n3000,000\n2,47\n7.410,00\n$                           \n4000,000\n4,48\n17.920,00\n$                         \n12000,000\n2,40\n28.800,00\n$                         \n27.000,00\n89.970,00\nUSD                   \n89.970,00\n$                         \nADVANCE PAYMENT OF 30% PAID ON NOVEMBER 7TH, 2025:\n26.956,00\n$               \nBALANCE TO PAID AGAINST COPY OF DOCUMENTS:\n63.014,00\n$               \nPort of loading: \nNAVEGANTES, SC, BR\nPort of discharge: \nHONG KONG, HK\nIncoterm:\nCFR\nFreight: \nPREPAID\nVessel / Voyage: \nCMA CGM BELEM 0BDMDE1MA\nNet Weight:\n27.000,00 KG\nGross Weight:\n,00 KG\nActual m3: \n,00 M³\nContainers nº: \n1x40' HC / GCXU8012525\nNCM: \nSOUTH SERVICE TRADING S/A\nEIGHTY-NINE THOUSAND NINE HUNDRED HUNDRED SEVENTY US DOLLARS 00/100.\nPLEASE SEND THE PAYMENT DIRECTLY TO:\nPAY TO (Intermediary Bank) : STANDARD CHARTERED BANK\nNEW YORK - NY - USA\nAGÊNCIA: 280 / CONTA: 24562-2\nPORTO ALEGRE - RS - BRASIL\nDETAILS OF CHARGES (71A): OUR\nPayment Terms: TT 30% USD IN ADVANCE AND 70% COPY BL\nSWIFT CODE: SCBLUS33 ACCOUNT NR: 3544-030205-001\nBENEFICIARY´S BANK: BANCO ITAÚ BBA S.A.\nSÃO PAULO - SP - BRASIL\nSWIFT CODE: ITAUBRSPNHO IBAN: BR29 6070 1190 0028 0000 0245 622C 1\nFURTHER CREDIT: SOUTH SERVICE TRADING S/A\nTOTAL CFR    \nDescription of Goods \nFROZEN BEEF AORTA\nTOTAL\nFREIGHT \nINSURANCE\nTOTAL FOB\nCOMMERCIAL INVOICE\nFROZEN BEEF OMASUM\nFROZEN BEEF TENDON\nFROZEN BEEF TRIPES\nFROZEN BEEF HONEYCOMB\n\nBENEFICIARY/SHIPPER:\nSouth Service Trading S/A\nAv. Cristovao Colombo,  1700  - CJ 201\nCNPJ: 93.101.632/0001-22  –  Porto Alegre/RS/Brasil\nFone 55 51 3393.5200  \nHome Page: www.southservice.com.br\nInvoice No: 396414\nIssued Date: November 12th, 2025\nAplicant: \nConsigned:\nBRAVO\t\nINTERNATIONAL DISTRIBUTION LLC\nCREATIVE LOGISTICS GLOBAL LIMITED\n15805 BISCAYNE BLVD - SUITE 201\nRM 703A, 7/F, PROFIT INDUSTRIAL BUILDING\nAVENTURA\nNO. 1-15, KWAI FUNG CRESCENT, KWAI CHUNG, N.T.\nFLORIDA, 33160\nHONG KONG\nDescription of Goods: 01 x 40 REFFER CONTAINER SAID TO CONTAIN 1069 CARTONS BOXES CONTAINING \nFROZEN FOODSTUFF COOKED\nAS PER PROFORMA INVOICE 090/2025 AS FOLLOWS:\nPurchase Order: PR 36554-25\nDescription of Goods \nKG\nCARTONS\nNET WEIGHT\nGROSS WEIGHT\nCONTANIER\nTARE\nSEAL\nFROZEN BEEF AORTA\n2000,000\n2.000,000\nFROZEN BEEF OMASUM\n6000,000\n6.000,000\nFROZEN BEEF TENDON\n3000,000\n3.000,000\nFROZEN BEEF HONEYCOMB\n4000,000\n4.000,000\nFROZEN BEEF TRIPES\n12000,000\n12.000,000\nTOTAL\n27000,000\n0\n27.000,00\n0,000\nIncoterm:\nCFR\nPort of loading: \nNAVEGANTES, SC, BR\nPort of discharge: \nHONG KONG, HK\nFreight: \nPREPAID\nVessel / Voyage: \nCMA CGM BELEM 0BDMDE1MA\nNet Weight:\n27.000,00 KG\nGross Weight:\n,00 KG\nActual m3: \n,00 M³\nNCM: \n0\nSOUTH SERVICE TRADING S/A\nPACKING LIST FOR COMMERCIAL INVOICE\nBZ094568\n4450\nGCXU8012525\n",
  "lines": [
    "SHIPPER/VENDOR South Service Trading S/A Av. Cristovao Colombo, 1700 - CJ 201 CNPJ: 93.101.632/0001-22 – Porto Alegre/RS/Brasil Fone 55 51 3393.5200 Home Page: www.southservice.com.br",
    "COMMERCIAL INVOICE",
    "Invoice No: 396414",
    "Issued Date: November 12th, 2025",
    "Aplicant: BRAVO INTERNATIONAL DISTRIBUTION LLC 15805 BISCAYNE BLVD - SUITE 201 AVENTURA FLORIDA, 33160 UNITED STATES OF AMERICA",
    "Consignee / Notify CREATIVE LOGISTICS GLOBAL LIMITED RM 703A, 7/F, PROFIT INDUSTRIAL BUILDING NO. 1-15, KWAI FUNG CRESCENT, KWAI CHUNG, N.T. HONG KONG",
    "Description of Goods:",
    "01 x 40 REFFER CONTAINER SAID TO CONTAIN 1069 CARTONS BOXES CONTAINING FROZEN FOODSTUFF COOKED AS PER PROFORMA INVOICE 090/2025 AS FOLLOWS:",
    "Purchase Order: PR 36554-25",
    "Description of Goods",
    "KG",
    "Unit Price - USD",
    "Subtotal Price - USD",
    "FROZEN BEEF AORTA FROZEN BEEF OMASUM FROZEN BEEF TENDON FROZEN BEEF HONEYCOMB FROZEN BEEF TRIPES TOTAL",
    "2000,000 6000,000 3000,000 4000,000 12000,000 27.000,00",
    "4,48 4,48 2,47 4,48 2,40",
    "$ $ $ $ $",
    "8.960,00 26.880,00 7.410,00 17.920,00 28.800,00",
    "TOTAL FOB FREIGHT INSURANCE TOTAL CFR",
    "USD",
    "$",
    "89.970,00",
    "89.970,00",
    "EIGHTY-NINE THOUSAND NINE HUNDRED HUNDRED SEVENTY US DOLLARS 00/100.",
    "ADVANCE PAYMENT OF 30% PAID ON NOVEMBER 7TH, 2025: BALANCE TO PAID AGAINST COPY OF DOCUMENTS:",
    "$ $",
    "26.956,00 63.014,00",
    "Payment Terms: TT 30% USD IN ADVANCE AND 70% COPY BL",
    "PLEASE SEND THE PAYMENT DIRECTLY TO: PAY TO (Intermediary Bank) : STANDARD CHARTERED BANK NEW YORK - NY - USA SWIFT CODE: SCBLUS33 ACCOUNT NR: 3544-030205-001 BENEFICIARY´S BANK: BANCO ITAÚ BBA S.A. SÃO PAULO - SP - BRASIL SWIFT CODE: ITAUBRSPNHO IBAN: BR29 6070 1190 0028 0000 0245 622C 1 FURTHER CREDIT: SOUTH SERVICE TRADING S/A AGÊNCIA: 280 / CONTA: 24562-2 PORTO ALEGRE - RS - BRASIL DETAILS OF CHARGES (71A): OUR",
    "Port of loading: Port of discharge: HONG KONG, HK Incoterm: Freight: Vessel / Voyage: Net Weight: Gross Weight: Actual m3: Containers nº: NCM:",
    "NAVEGANTES, SC, BR",
    "CFR PREPAID CMA CGM BELEM 0BDMDE1MA 27.000,00 KG ,00 KG ,00 M³ 1x40' HC / GCXU8012525",
    "SOUTH SERVICE TRADING S/A",
    "BENEFICIARY/SHIPPER: South Service Trading S/A Av. Cristovao Colombo, 1700 - CJ 201 CNPJ: 93.101.632/0001-22 – Porto Alegre/RS/Brasil Fone 55 51 3393.5200 Home Page: www.southservice.com.br",
    "PACKING LIST FOR COMMERCIAL INVOICE",
    "Invoice No: 396414",
    "Issued Date: November 12th, 2025",
    "Aplicant: BRAVO INTERNATIONAL DISTRIBUTION LLC 15805 BISCAYNE BLVD - SUITE 201 AVENTURA FLORIDA, 33160",
    "Consigned: CREATIVE LOGISTICS GLOBAL LIMITED RM 703A, 7/F, PROFIT INDUSTRIAL BUILDING NO. 1-15, KWAI FUNG CRESCENT, KWAI CHUNG, N.T. HONG KONG",
    "Description of Goods: 01 x 40 REFFER CONTAINER SAID TO CONTAIN 1069 CARTONS BOXES CONTAINING",
    "FROZEN FOODSTUFF COOKED AS PER PROFORMA INVOICE 090/2025 AS FOLLOWS:",
    "Purchase Order: PR 36554-25",
    "Description of Goods FROZEN BEEF AORTA FROZEN BEEF OMASUM FROZEN BEEF TENDON FROZEN BEEF HONEYCOMB FROZEN BEEF TRIPES TOTAL",
    "KG 2000,000 6000,000 3000,000 4000,000 12000,000 27000,000",
    "CARTONS",
    "0",
    "NET WEIGHT 2.000,000 6.000,000 3.000,000 4.000,000 12.000,000 27.000,00",
    "GROSS WEIGHT CONTANIER",
    "GCXU8012525",
    "0,000",
    "Incoterm: Port of loading: Port of discharge: Freight: Vessel / Voyage: Net Weight: Gross Weight: Actual m3: NCM:",
    "CFR NAVEGANTES, SC, BR HONG KONG, HK PREPAID CMA CGM BELEM 0BDMDE1MA 27.000,00 KG ,00 KG ,00 M³",
    "0",
    "SOUTH SERVICE TRADING S/A",
    "TARE",
    "4450",
    "SEAL",
    "BZ094568",
    "SHIPPER/VENDOR",
    "South Service Trading S/A",
    "Av. Cristovao Colombo, 1700 - CJ 201",
    "CNPJ: 93.101.632/0001-22 – Porto Alegre/RS/Brasil",
    "Fone 55 51 3393.5200",
    "Home Page: www.southservice.com.br",
    "COMMERCIAL INVOICE",
    "Invoice No: 396414 Issued Date: November 12th, 2025",
    "Aplicant: Consignee / Notify",
    "BRAVO INTERNATIONAL DISTRIBUTION LLC CREATIVE LOGISTICS GLOBAL LIMITED",
    "15805 BISCAYNE BLVD - SUITE 201 RM 703A, 7/F, PROFIT INDUSTRIAL BUILDING",
    "AVENTURA NO. 1-15, KWAI FUNG CRESCENT, KWAI CHUNG, N.T.",
    "FLORIDA, 33160 HONG KONG",
    "UNITED STATES OF AMERICA",
    "Description of Goods: 01 x 40 REFFER CONTAINER SAID TO CONTAIN 1069 CARTONS BOXES CONTAINING",
    "FROZEN FOODSTUFF COOKED",
    "AS PER PROFORMA INVOICE 090/2025 AS FOLLOWS:",
    "Purchase Order: PR 36554-25",
    "Description of Goods KG Unit Price - USD Subtotal Price - USD",
    "FROZEN BEEF AORTA 2000,000 4,48 $ 8 .960,00",
    "FROZEN BEEF OMASUM 6000,000 4,48 $ 2 6.880,00",
    "FROZEN BEEF TENDON 3000,000 2,47 $ 7 .410,00",
    "FROZEN BEEF HONEYCOMB 4000,000 4,48 $ 1 7.920,00",
    "FROZEN BEEF TRIPES 12000,000 2,40 $ 2 8.800,00",
    "TOTAL 27.000,00",
    "TOTAL FOB USD 8 9.970,00",
    "FREIGHT",
    "INSURANCE",
    "TOTAL CFR $ 8 9.970,00",
    "EIGHTY-NINE THOUSAND NINE HUNDRED HUNDRED SEVENTY US DOLLARS 00/100.",
    "ADVANCE PAYMENT OF 30% PAID ON NOVEMBER 7TH, 2025: $ 26.956,00",
    "BALANCE TO PAID AGAINST COPY OF DOCUMENTS: $ 63.014,00",
    "Payment Terms: TT 30% USD IN ADVANCE AND 70% COPY BL",
    "PLEASE SEND THE PAYMENT DIRECTLY TO:",
    "PAY TO (Intermediary Bank) : STANDARD CHARTERED BANK",
    "NEW YORK - NY - USA",
    "SWIFT CODE: SCBLUS33 ACCOUNT NR: 3544-030205-001",
    "BENEFICIARY´S BANK: BANCO ITAÚ BBA S.A.",
    "SÃO PAULO - SP - BRASIL",
    "SWIFT CODE: ITAUBRSPNHO IBAN: BR29 6070 1190 0028 0000 0245 622C 1",
    "FURTHER CREDIT: SOUTH SERVICE TRADING S/A",
    "AGÊNCIA: 280 / CONTA: 24562-2",
    "PORTO ALEGRE - RS - BRASIL",
    "DETAILS OF CHARGES (71A): OUR",
    "Port of loading: NAVEGANTES, SC, BR",
    "Port of discharge: HONG KONG, HK",
    "Incoterm: CFR",
    "Freight: PREPAID",
    "Vessel / Voyage: CMA CGM BELEM 0BDMDE1MA",
    "Net Weight: 27.000,00 KG",
    "Gross Weight: ,00 KG",
    "Actual m3: ,00 M³",
    "Containers nº: 1x40' HC / GCXU8012525",
    "NCM:",
    "SOUTH SERVICE TRADING S/A",
    "BENEFICIARY/SHIPPER:",
    "South Service Trading S/A",
    "Av. Cristovao Colombo, 1700 - CJ 201",
    "CNPJ: 93.101.632/0001-22 – Porto Alegre/RS/Brasil",
    "Fone 55 51 3393.5200",
    "Home Page: www.southservice.com.br",
    "PACKING LIST FOR COMMERCIAL INVOICE",
    "Invoice No: 396414 Issued Date: November 12th, 2025",
    "Aplicant: Consigned:",
    "BRAVOI NTERNATIONAL DISTRIBUTION LLC CREATIVE LOGISTICS GLOBAL LIMITED",
    "15805 BISCAYNE BLVD - SUITE 201 RM 703A, 7/F, PROFIT INDUSTRIAL BUILDING",
    "AVENTURA NO. 1-15, KWAI FUNG CRESCENT, KWAI CHUNG, N.T.",
    "FLORIDA, 33160 HONG KONG",
    "Description of Goods: 01 x 40 REFFER CONTAINER SAID TO CONTAIN 1069 CARTONS BOXES CONTAINING",
    "FROZEN FOODSTUFF COOKED",
    "AS PER PROFORMA INVOICE 090/2025 AS FOLLOWS:",
    "Purchase Order: PR 36554-25",
    "Description of Goods KG CARTONS NET WEIGHT GROSS WEIGHT CONTANIER TARE SEAL",
    "FROZEN BEEF AORTA 2000,000 2.000,000",
    "FROZEN BEEF OMASUM 6000,000 6.000,000",
    "FROZEN BEEF TENDON 3000,000 3.000,000 GCXU8012525 4450 BZ094568",
    "FROZEN BEEF HONEYCOMB 4000,000 4.000,000",
    "FROZEN BEEF TRIPES 12000,000 12.000,000",
    "TOTAL 27000,000 0 27.000,00 0,000",
    "Incoterm: CFR",
    "Port of loading: NAVEGANTES, SC, BR",
    "Port of discharge: HONG KONG, HK",
    "Freight: PREPAID",
    "Vessel / Voyage: CMA CGM BELEM 0BDMDE1MA",
    "Net Weight: 27.000,00 KG",
    "Gross Weight: ,00 KG",
    "Actual m3: ,00 M³",
    "NCM: 0",
    "SOUTH SERVICE TRADING S/A",
    "SHIPPER/VENDOR",
    "South Service Trading S/A",
    "Av. Cristovao Colombo, 1700 - CJ 201",
    "CNPJ: 93.101.632/0001-22 – Porto Alegre/RS/Brasil",
    "Fone 55 51 3393.5200",
    "Home Page: www.southservice.com.br",
    "Invoice No: 396414",
    "Issued Date: November 12th, 2025",
    "Aplicant:",
    "Consignee / Notify",
    "BRAVO INTERNATIONAL DISTRIBUTION LLC",
    "CREATIVE LOGISTICS GLOBAL LIMITED",
    "15805 BISCAYNE BLVD - SUITE 201",
    "RM 703A, 7/F, PROFIT INDUSTRIAL BUILDING",
    "AVENTURA",
    "NO. 1-15, KWAI FUNG CRESCENT, KWAI CHUNG, N.T.",
    "FLORIDA, 33160",
    "HONG KONG",
    "UNITED STATES OF AMERICA",
    "Description of Goods:",
    "01 x 40 REFFER CONTAINER SAID TO CONTAIN 1069 CARTONS BOXES CONTAINING",
    "FROZEN FOODSTUFF COOKED",
    "AS PER PROFORMA INVOICE 090/2025 AS FOLLOWS:",
    "Purchase Order: PR 36554-25",
    "KG",
    "Unit Price - USD",
    "Subtotal Price - USD",
    "2000,000",
    "4,48",
    "8.960,00",
    "$",
    "6000,000",
    "4,48",
    "26.880,00",
    "$",
    "3000,000",
    "2,47",
    "7.410,00",
    "$",
    "4000,000",
    "4,48",
    "17.920,00",
    "$",
    "12000,000",
    "2,40",
    "28.800,00",
    "$",
    "27.000,00",
    "89.970,00",
    "USD",
    "89.970,00",
    "$",
    "ADVANCE PAYMENT OF 30% PAID ON NOVEMBER 7TH, 2025:",
    "26.956,00",
    "$",
    "BALANCE TO PAID AGAINST COPY OF DOCUMENTS:",
    "63.014,00",
    "$",
    "Port of loading:",
    "NAVEGANTES, SC, BR",
    "Port of discharge:",
    "HONG KONG, HK",
    "Incoterm:",
    "CFR",
    "Freight:",
    "PREPAID",
    "Vessel / Voyage:",
    "CMA CGM BELEM 0BDMDE1MA",
    "Net Weight:",
    "27.000,00 KG",
    "Gross Weight:",
    ",00 KG",
    "Actual m3:",
    ",00 M³",
    "Containers nº:",
    "1x40' HC / GCXU8012525",
    "NCM:",
    "SOUTH SERVICE TRADING S/A",
    "EIGHTY-NINE THOUSAND NINE HUNDRED HUNDRED SEVENTY US DOLLARS 00/100.",
    "PLEASE SEND THE PAYMENT DIRECTLY TO:",
    "PAY TO (Intermediary Bank) : STANDARD CHARTERED BANK",
    "NEW YORK - NY - USA",
    "AGÊNCIA: 280 / CONTA: 24562-2",
    "PORTO ALEGRE - RS - BRASIL",
    "DETAILS OF CHARGES (71A): OUR",
    "Payment Terms: TT 30% USD IN ADVANCE AND 70% COPY BL",
    "SWIFT CODE: SCBLUS33 ACCOUNT NR: 3544-030205-001",
    "BENEFICIARY´S BANK: BANCO ITAÚ BBA S.A.",
    "SÃO PAULO - SP - BRASIL",
    "SWIFT CODE: ITAUBRSPNHO IBAN: BR29 6070 1190 0028 0000 0245 622C 1",
    "FURTHER CREDIT: SOUTH SERVICE TRADING S/A",
    "TOTAL CFR",
    "Description of Goods",
    "FROZEN BEEF AORTA",
    "TOTAL",
    "FREIGHT",
    "INSURANCE",
    "TOTAL FOB",
    "COMMERCIAL INVOICE",
    "FROZEN BEEF OMASUM",
    "FROZEN BEEF TENDON",
    "FROZEN BEEF TRIPES",
    "FROZEN BEEF HONEYCOMB",
    "BENEFICIARY/SHIPPER:",
    "South Service Trading S/A",
    "Av. Cristovao Colombo, 1700 - CJ 201",
    "CNPJ: 93.101.632/0001-22 – Porto Alegre/RS/Brasil",
    "Fone 55 51 3393.5200",
    "Home Page: www.southservice.com.br",
    "Invoice No: 396414",
    "Issued Date: November 12th, 2025",
    "Aplicant:",
    "Consigned:",
    "BRAVO",
    "INTERNATIONAL DISTRIBUTION LLC",
    "CREATIVE LOGISTICS GLOBAL LIMITED",
    "15805 BISCAYNE BLVD - SUITE 201",
    "RM 703A, 7/F, PROFIT INDUSTRIAL BUILDING",
    "AVENTURA",
    "NO. 1-15, KWAI FUNG CRESCENT, KWAI CHUNG, N.T.",
    "FLORIDA, 33160",
    "HONG KONG",
    "Description of Goods: 01 x 40 REFFER CONTAINER SAID TO CONTAIN 1069 CARTONS BOXES CONTAINING",
    "FROZEN FOODSTUFF COOKED",
    "AS PER PROFORMA INVOICE 090/2025 AS FOLLOWS:",
    "Purchase Order: PR 36554-25",
    "Description of Goods",
    "KG",
    "CARTONS",
    "NET WEIGHT",
    "GROSS WEIGHT",
    "CONTANIER",
    "TARE",
    "SEAL",
    "FROZEN BEEF AORTA",
    "2000,000",
    "2.000,000",
    "FROZEN BEEF OMASUM",
    "6000,000",
    "6.000,000",
    "FROZEN BEEF TENDON",
    "3000,000",
    "3.000,000",
    "FROZEN BEEF HONEYCOMB",
    "4000,000",
    "4.000,000",
    "FROZEN BEEF TRIPES",
    "12000,000",
    "12.000,000",
    "TOTAL",
    "27000,000",
    "0",
    "27.000,00",
    "0,000",
    "Incoterm:",
    "CFR",
    "Port of loading:",
    "NAVEGANTES, SC, BR",
    "Port of discharge:",
    "HONG KONG, HK",
    "Freight:",
    "PREPAID",
    "Vessel / Voyage:",
    "CMA CGM BELEM 0BDMDE1MA",
    "Net Weight:",
    "27.000,00 KG",
    "Gross Weight:",
    ",00 KG",
    "Actual m3:",
    ",00 M³",
    "NCM:",
    "0",
    "SOUTH SERVICE TRADING S/A",
    "PACKING LIST FOR COMMERCIAL INVOICE",
    "BZ094568",
    "4450",
    "GCXU8012525"
  ],
  "blocks_extracted": {
    "Shipper": [
      "VENDOR",
      "VENDOR"
    ],
    "Date": [
      ": November 12th, 2025",
      ": November 12th, 2025",
      ": November 12th, 2025",
      ": November 12th, 2025"
    ],
    "Consignee": [
      "AVENTURA NO. 1-15, KWAI FUNG CRESCENT, KWAI CHUNG, N.T. UNITED STATES OF AMERICA",
      "CREATIVE LOGISTICS GLOBAL LIMITED RM 703A, 7/F, PROFIT INDUSTRIAL BUILDING AVENTURA NO. 1-15, KWAI FUNG CRESCENT, KWAI CHUNG, N.T. HONG KONG UNITED STATES OF AMERICA"
    ],
    "Notify": [
      "AVENTURA NO. 1-15, KWAI FUNG CRESCENT, KWAI CHUNG, N.T. UNITED STATES OF AMERICA",
      "CREATIVE LOGISTICS GLOBAL LIMITED RM 703A, 7/F, PROFIT INDUSTRIAL BUILDING AVENTURA NO. 1-15, KWAI FUNG CRESCENT, KWAI CHUNG, N.T. HONG KONG UNITED STATES OF AMERICA"
    ],
    "Invoice": [
      "396414",
      "No: 396414",
      "No: 396414",
      "396414",
      "No: 396414 Issued Date: November 12th, 2025",
      "No: 396414 Issued Date: November 12th, 2025",
      "No: 396414",
      "396414",
      "No: 396414"
    ],
    "P.O n": [
      ": PR 36554-25",
      ": PR 36554-25",
      ": PR 36554-25",
      ": PR 36554-25",
      ": PR 36554-25",
      ": PR 36554-25"
    ],
    "Terms of Payment": [
      ": TT 30% USD IN ADVANCE AND 70% COPY BL",
      ": TT 30% USD IN ADVANCE AND 70% COPY BL",
      ": TT 30% USD IN ADVANCE AND 70% COPY BL"
    ],
    "Bill of Lading": [],
    "Vessel/Voyage No.": [
      "e: CMA CGM BELEM 0BDMDE1MA",
      "e: CMA CGM BELEM 0BDMDE1MA",
      "e:",
      "e:"
    ],
    "Sailing Dated": [],
    "Shipping Company": [],
    "Currency": [],
    "Port of Loading": [
      "NAVEGANTES, SC, BR"
    ],
    "Port of Discharge": [
      ": HONG KONG, HK",
      ": HONG KONG, HK",
      ":",
      ":"
    ],
    "Place of Delivery": [],
    "Container": [
      "s nº: 1x40' HC / GCXU8012525",
      "s nº:"
    ],
    "Tare": [
      "4450"
    ],
    "Seal": [
      "BZ094568",
      "FROZEN BEEF AORTA 2000,000 2.000,000 FROZEN BEEF OMASUM 6000,000 6.000,000 FROZEN BEEF TENDON 3000,000 3.000,000 FROZEN BEEF HONEYCOMB 4000,000 4.000,000"
    ],
    "Description of Goods": [
      ":",
      "KG Unit Price - USD Subtotal Price - USD FROZEN BEEF AORTA FROZEN BEEF OMASUM FROZEN BEEF TENDON FROZEN BEEF HONEYCOMB FROZEN BEEF TRIPES TOTAL 2000,000 6000,000 3000,000 4000,000 12000,000 27.000,00 4,48 4,48 2,47 4,48 2,40 $ $ $ $ $ 8.960,00 26.880,00 7.410,00 17.920,00 28.800,00",
      ": 01 x 40 REFFER CONTAINER SAID TO CONTAIN 1069 CARTONS BOXES CONTAINING",
      "FROZEN BEEF AORTA FROZEN BEEF OMASUM FROZEN BEEF TENDON FROZEN BEEF HONEYCOMB FROZEN BEEF TRIPES TOTAL",
      ": 01 x 40 REFFER CONTAINER SAID TO CONTAIN 1069 CARTONS BOXES CONTAINING",
      "KG Unit Price - USD Subtotal Price - USD",
      ": 01 x 40 REFFER CONTAINER SAID TO CONTAIN 1069 CARTONS BOXES CONTAINING",
      "KG CARTONS NET WEIGHT GROSS WEIGHT CONTANIER TARE SEAL",
      ":",
      "FROZEN BEEF AORTA TOTAL FREIGHT INSURANCE",
      ": 01 x 40 REFFER CONTAINER SAID TO CONTAIN 1069 CARTONS BOXES CONTAINING",
      "KG CARTONS"
    ],
    "NCM": [
      ":",
      ": 0",
      ":",
      ":"
    ],
    "Marks And Numbers": [],
    "No. of Packages": [],
    "Gross Weight": [
      "CONTANIER",
      ": ,00 KG",
      ": ,00 KG",
      ":",
      "CONTANIER",
      ":"
    ],
    "Net Weight": [
      "2.000,000 6.000,000 3.000,000 4.000,000 12.000,000 27.000,00",
      ": 27.000,00 KG",
      ": 27.000,00 KG",
      ":",
      ":"
    ],
    "Measurement": [
      ": ,00 M³",
      ": ,00 M³",
      ":",
      ":"
    ],
    "Type of Freight": [
      ": Port of loading: Port of discharge: Freight: Vessel / Voyage: Net Weight: Gross Weight: Actual m3: NCM:",
      ": CFR",
      ": CFR",
      ":",
      ":"
    ],
    "Total Price": [
      "FREIGHT INSURANCE TOTAL CFR",
      "USD 8 9.970,00",
      "$ 8 9.970,00"
    ]
  },
  "regex_extracted": {
    "Shipper": [
      "VENDOR South Service Trading S/A Av. Cristovao Colombo, 1700 - CJ 201 CNPJ: 93.101.632/0001-22 – Porto Alegre/RS/Brasil Fone 55 51 3393.5200 Home Page: www.southservice.com.br",
      "South Service Trading S/A Av. Cristovao Colombo, 1700 - CJ 201 CNPJ: 93.101.632/0001-22 – Porto Alegre/RS/Brasil Fone 55 51 3393.5200 Home Page: www.southservice.com.br"
    ],
    "Date": [
      "November 12th, 2025",
      "November 12th, 2025",
      "November 12th, 2025",
      "November 12th, 2025"
    ],
    "Consignee": [
      "CREATIVE LOGISTICS GLOBAL LIMITED RM 703A, 7/F, PROFIT INDUSTRIAL BUILDING NO. 1-15, KWAI FUNG CRESCENT, KWAI CHUNG, N.T. HONG KONG"
    ],
    "Notify": [
      "CREATIVE LOGISTICS GLOBAL LIMITED RM 703A, 7/F, PROFIT INDUSTRIAL BUILDING NO. 1-15, KWAI FUNG CRESCENT, KWAI CHUNG, N.T. HONG KONG",
      "CREATIVE LOGISTICS GLOBAL LIMITED RM 703A, 7/F, PROFIT INDUSTRIAL BUILDING NO. 1-15, KWAI FUNG CRESCENT, KWAI CHUNG, N.T. HONG KONG"
    ],
    "Invoice": [
      "396414",
      "396414"
    ],
    "P.O n": [
      "PR 36554-25",
      "PR 36554-25"
    ],
    "Terms of Payment": [],
    "Bill of Lading": [],
    "Vessel/Voyage No.": [],
    "Sailing Dated": [],
    "Shipping Company": [],
    "Currency": [],
    "Port of Loading": [],
    "Port of Discharge": [],
    "Place of Delivery": [],
    "Container": [],
    "Tare": [
      "4450",
      "4450"
    ],
    "Seal": [
      "BZ094568",
      "BZ094568"
    ],
    "Description of Goods": [],
    "NCM": [
      "NAVEGANTES, SC, BR",
      "NAVEGANTES, SC, BR"
    ],
    "Marks And Numbers": [],
    "No. of Packages": [],
    "Gross Weight": [],
    "Net Weight": [],
    "Measurement": [
      "1x40' HC / GCXU8012525"
    ],
    "Type of Freight": [],
    "Total Price": [
      "USD",
      "USD",
      "USD"
    ]
  },
  "final_after_combine": {
    "Shipper": "VENDOR",
    "Date": ": November 12th, 2025",
    "Consignee": "AVENTURA NO. 1-15, KWAI FUNG CRESCENT, KWAI CHUNG, N.T. UNITED STATES OF AMERICA",
    "Notify": "AVENTURA NO. 1-15, KWAI FUNG CRESCENT, KWAI CHUNG, N.T. UNITED STATES OF AMERICA",
    "Invoice": "396414",
    "P.O n": ": PR 36554-25",
    "Terms of Payment": ": TT 30% USD IN ADVANCE AND 70% COPY BL",
    "Bill of Lading": "Não Encontrado",
    "Vessel/Voyage No.": "e: CMA CGM BELEM 0BDMDE1MA",
    "Sailing Dated": "Não Encontrado",
    "Shipping Company": "Não Encontrado",
    "Currency": "Não Encontrado",
    "Port of Loading": "NAVEGANTES, SC, BR",
    "Port of Discharge": ": HONG KONG, HK",
    "Place of Delivery": ": HONG KONG, HK",
    "Container": "s nº: 1x40' HC / GCXU8012525",
    "Tare": "4450",
    "Seal": "BZ094568",
    "Description of Goods": ":",
    "NCM": ":",
    "Marks And Numbers": "Não Encontrado",
    "No. of Packages": "Não Encontrado",
    "Gross Weight": "CONTANIER",
    "Net Weight": "2.000,000 6.000,000 3.000,000 4.000,000 12.000,000 27.000,00",
    "Measurement": ": ,00 M³",
    "Type of Freight": ": Port of loading: Port of discharge: Freight: Vessel / Voyage: Net Weight: Gross Weight: Actual m3: NCM:",
    "Total Price": "FREIGHT INSURANCE TOTAL CFR"
  }
}